MANIFEST.in
README.md
setup.cfg
setup.py
cython_bbox_nguyenchien.egg-info/PKG-INFO
cython_bbox_nguyenchien.egg-info/SOURCES.txt
cython_bbox_nguyenchien.egg-info/dependency_links.txt
cython_bbox_nguyenchien.egg-info/top_level.txt
src/cython_bbox.c
src/cython_bbox.pyx