Metadata-Version: 2.1
Name: cython-bbox-nguyenchien
Version: 0.1.3
Summary: Standalone cython_bbox
Home-page: https://github.com/firefliesqn1102/first_package.git
Author: Chien
Author-email: firefliesqn1102@gmail.com
License: UNKNOWN
Keywords: cython_bbox_nguyenchien
Platform: UNKNOWN
